HuaxiaZhichengPmpKaoshiFudaoPeixunChengangFix1/README.md
HuaxiaZhichengPmpKaoshiFudaoPeixunChengangFix1/__init__.py
HuaxiaZhichengPmpKaoshiFudaoPeixunChengangFix1/__main__.py
HuaxiaZhichengPmpKaoshiFudaoPeixunChengangFix1/file.pdf
HuaxiaZhichengPmpKaoshiFudaoPeixunChengangFix1/index.html
huaxia_zhicheng_pmp_kaoshi_fudao_peixun_chengang_fix1-2025.3.25.0.dist-info/METADATA
huaxia_zhicheng_pmp_kaoshi_fudao_peixun_chengang_fix1-2025.3.25.0.dist-info/WHEEL
huaxia_zhicheng_pmp_kaoshi_fudao_peixun_chengang_fix1-2025.3.25.0.dist-info/entry_points.txt
huaxia_zhicheng_pmp_kaoshi_fudao_peixun_chengang_fix1-2025.3.25.0.dist-info/top_level.txt
huaxia_zhicheng_pmp_kaoshi_fudao_peixun_chengang_fix1-2025.3.25.0.dist-info/RECORD
